SecondPy/__init__.py
SecondPy/test.py
TestPythonPackaging-1.2.0.dist-info/DESCRIPTION.rst
TestPythonPackaging-1.2.0.dist-info/METADATA
TestPythonPackaging-1.2.0.dist-info/RECORD
TestPythonPackaging-1.2.0.dist-info/WHEEL
TestPythonPackaging-1.2.0.dist-info/metadata.json
TestPythonPackaging-1.2.0.dist-info/top_level.txt
