Metadata-Version: 2.0
Name: TestPythonPackaging
Version: 1.2.0
Summary: SmallDescription
Home-page: UNKNOWN
Author: Othmane Lahrimi
Author-email: lahrimi.oth1996@live.fr
License: UNKNOWN
Platform: UNKNOWN
